{"ior":{"uuid":"9d922c3a-7573-4494-99ef-cba60dac0677","component":"Unit","version":"0.3.22.1"},"owner":"system","model":{"uuid":"9d922c3a-7573-4494-99ef-cba60dac0677","name":"UnitModel.interface.ts","typeM3":"CLASS","origin":"ior:git:github.com/Cerulean-Circle-GmbH/UpDown/blob/dev/web4v0100/components/ONCE/0.3.22.1/src/ts/layer3/UnitModel.interface.ts","definition":"TypeScript UnitModel.interface class/interface","filePath":"src/ts/layer3/UnitModel.interface.ts","mimetype":"text/typescript","createdAt":"2026-01-01T19:00:58.835Z","updatedAt":"2026-01-01T19:00:58.835Z","indexPath":"/Users/Shared/Workspaces/2cuGitHub/UpDown/scenarios/index/9/d/9/2/2/9d922c3a-7573-4494-99ef-cba60dac0677.scenario.json","symlinkPaths":["type/Unit/0.3.22.1"]},"unit":{"indexPath":"9/d/9/2/2/9d922c3a-7573-4494-99ef-cba60dac0677.scenario.json","symlinkPaths":["type/Unit/0.3.22.1"],"references":[],"schemaVersion":"1.1.0","createdBy":"Unit/0.3.22.1","createdAt":"2026-01-01T19:00:58.835Z","updatedAt":"2026-01-01T19:00:58.835Z"}}