{
  "ior": {
    "uuid": "53bcc30f-cdd7-43ba-8d45-406373ced4cc",
    "component": "Unit",
    "version": "0.3.22.2"
  },
  "owner": "system",
  "model": {
    "uuid": "53bcc30f-cdd7-43ba-8d45-406373ced4cc",
    "name": "LifecycleManager.interface.ts",
    "typeM3": "CLASS",
    "origin": "ior:git:github.com/Cerulean-Circle-GmbH/UpDown/blob/dev/web4v0100/components/ONCE/0.3.22.2/src/ts/layer3/LifecycleManager.interface.ts",
    "definition": "TypeScript LifecycleManager.interface class/interface",
    "filePath": "src/ts/layer3/LifecycleManager.interface.ts",
    "mimetype": "text/typescript",
    "createdAt": "2026-01-06T11:44:03.815Z",
    "updatedAt": "2026-01-06T11:44:03.816Z",
    "indexPath": "/Users/Shared/Workspaces/2cuGitHub/UpDown/scenarios/index/5/3/b/c/c/53bcc30f-cdd7-43ba-8d45-406373ced4cc.scenario.json",
    "symlinkPaths": [
      "type/Unit/0.3.22.2"
    ]
  },
  "unit": {
    "indexPath": "5/3/b/c/c/53bcc30f-cdd7-43ba-8d45-406373ced4cc.scenario.json",
    "symlinkPaths": [
      "type/Unit/0.3.22.2"
    ],
    "references": [],
    "schemaVersion": "1.1.0",
    "createdBy": "Unit/0.3.22.2",
    "createdAt": "2026-01-06T11:44:03.815Z",
    "updatedAt": "2026-01-06T11:44:03.815Z"
  }
}