{
  "ior": {
    "uuid": "49641bcb-6497-4ce8-a29d-7a4cb86ca407",
    "component": "Unit",
    "version": "0.3.22.2"
  },
  "owner": "system",
  "model": {
    "uuid": "49641bcb-6497-4ce8-a29d-7a4cb86ca407",
    "name": "CLI.interface.ts",
    "typeM3": "CLASS",
    "origin": "ior:git:github.com/Cerulean-Circle-GmbH/UpDown/blob/dev/web4v0100/components/ONCE/0.3.22.2/src/ts/layer3/CLI.interface.ts",
    "definition": "TypeScript CLI.interface class/interface",
    "filePath": "src/ts/layer3/CLI.interface.ts",
    "mimetype": "text/typescript",
    "createdAt": "2026-01-04T17:08:58.268Z",
    "updatedAt": "2026-01-04T17:08:58.268Z",
    "indexPath": "/Users/Shared/Workspaces/2cuGitHub/UpDown/scenarios/index/4/9/6/4/1/49641bcb-6497-4ce8-a29d-7a4cb86ca407.scenario.json",
    "symlinkPaths": [
      "type/Unit/0.3.22.2"
    ]
  },
  "unit": {
    "indexPath": "4/9/6/4/1/49641bcb-6497-4ce8-a29d-7a4cb86ca407.scenario.json",
    "symlinkPaths": [
      "type/Unit/0.3.22.2"
    ],
    "references": [],
    "schemaVersion": "1.1.0",
    "createdBy": "Unit/0.3.22.2",
    "createdAt": "2026-01-04T17:08:58.268Z",
    "updatedAt": "2026-01-04T17:08:58.268Z"
  }
}