{
  "ior": {
    "uuid": "286d9803-aac7-4f9d-901e-6f7c150f3f4c",
    "component": "ONCE",
    "version": "0.3.22.2"
  },
  "owner": "TsAstExtractor",
  "model": {
    "uuid": "286d9803-aac7-4f9d-901e-6f7c150f3f4c",
    "name": "RewriteContext",
    "extends": null,
    "implements": [],
    "sourcePath": "src/ts/layer2/HeaderRewriter.ts",
    "indexPath": "scenarios/index/286d9803-aac7-4f9d-901e-6f7c150f3f4c.type.scenario.json",
    "symlinkPaths": [
      "scenarios/type/RewriteContext.type.scenario.json"
    ],
    "attributes": [
      {
        "name": "clientIp",
        "type": "string",
        "optional": true,
        "defaultValue": null
      },
      {
        "name": "originalHost",
        "type": "string",
        "optional": true,
        "defaultValue": null
      },
      {
        "name": "originalUrl",
        "type": "string",
        "optional": true,
        "defaultValue": null
      },
      {
        "name": "protocol",
        "type": "'http' | 'https'",
        "optional": true,
        "defaultValue": null
      }
    ],
    "properties": [],
    "references": [],
    "collections": [],
    "methods": [],
    "component": "ONCE",
    "version": "0.3.22.2",
    "createdAt": "2026-01-04T17:41:56.071Z",
    "updatedAt": "2026-01-04T17:41:56.071Z",
    "isInterface": true,
    "isAbstract": false
  }
}