{
  "ior": {
    "uuid": "46b87964-61bd-448e-ba74-0c8a93720fab",
    "component": "ONCE",
    "version": "0.3.22.2"
  },
  "owner": "TsAstExtractor",
  "model": {
    "uuid": "46b87964-61bd-448e-ba74-0c8a93720fab",
    "name": "IOROptions",
    "extends": null,
    "implements": [],
    "sourcePath": "src/ts/layer3/IOROptions.interface.ts",
    "indexPath": "scenarios/index/46b87964-61bd-448e-ba74-0c8a93720fab.type.scenario.json",
    "symlinkPaths": [
      "scenarios/type/IOROptions.type.scenario.json"
    ],
    "attributes": [
      {
        "name": "method",
        "type": "HttpMethod",
        "optional": true,
        "defaultValue": null
      },
      {
        "name": "headers",
        "type": "Record<string, string>",
        "optional": true,
        "defaultValue": null
      },
      {
        "name": "timeout",
        "type": "number",
        "optional": true,
        "defaultValue": null
      },
      {
        "name": "signal",
        "type": "AbortSignal",
        "optional": true,
        "defaultValue": null
      }
    ],
    "properties": [],
    "references": [],
    "collections": [
      {
        "name": "skipProtocols",
        "elementType": "string"
      }
    ],
    "methods": [],
    "component": "ONCE",
    "version": "0.3.22.2",
    "createdAt": "2026-01-04T15:55:02.867Z",
    "updatedAt": "2026-01-04T15:55:02.867Z",
    "isInterface": true,
    "isAbstract": false
  }
}