{"ior":{"uuid":"daa36f46-5cf2-40c4-838f-b13cc5a6e789","component":"ONCE","version":"0.3.22.1"},"owner":"TsAstExtractor","model":{"uuid":"daa36f46-5cf2-40c4-838f-b13cc5a6e789","name":"IORRoute","extends":"ior:esm:/ONCE/0.3.22.1/RouteModel","implements":[],"sourcePath":"src/ts/layer3/IORRoute.interface.ts","indexPath":"scenarios/index/daa36f46-5cf2-40c4-838f-b13cc5a6e789.type.scenario.json","symlinkPaths":["scenarios/type/IORRoute.type.scenario.json"],"attributes":[{"name":"componentName","type":"string","optional":true,"defaultValue":null},{"name":"version","type":"string","optional":true,"defaultValue":null},{"name":"instanceUuid","type":"string","optional":true,"defaultValue":null},{"name":"methodName","type":"string","optional":true,"defaultValue":null}],"properties":[],"references":[],"collections":[],"methods":[],"component":"ONCE","version":"0.3.22.1","createdAt":"2026-01-01T19:19:30.217Z","updatedAt":"2026-01-01T19:19:30.217Z","isInterface":true,"isAbstract":false}}