{
  "ior": {
    "uuid": "fda381c2-398d-4f67-b9bc-3a614fc31ad8",
    "component": "ONCE",
    "version": "0.3.22.2"
  },
  "owner": "TsAstExtractor",
  "model": {
    "uuid": "fda381c2-398d-4f67-b9bc-3a614fc31ad8",
    "name": "OnceServerStatusView",
    "extends": "ior:esm:/ONCE/0.3.22.2/UcpView",
    "implements": [],
    "sourcePath": "src/ts/layer5/views/OnceServerStatusView.ts",
    "indexPath": "scenarios/index/fda381c2-398d-4f67-b9bc-3a614fc31ad8.type.scenario.json",
    "symlinkPaths": [
      "scenarios/type/OnceServerStatusView.type.scenario.json"
    ],
    "attributes": [
      {
        "name": "cssPath",
        "type": "any",
        "optional": false,
        "defaultValue": "OnceServerStatusView.css"
      },
      {
        "name": "refreshing",
        "type": "boolean",
        "optional": false,
        "defaultValue": false
      }
    ],
    "properties": [
      {
        "name": "uptimeFormatted",
        "type": "string",
        "hasGetter": true,
        "hasSetter": false,
        "isReadonly": true
      },
      {
        "name": "memoryFormatted",
        "type": "string",
        "hasGetter": true,
        "hasSetter": false,
        "isReadonly": true
      },
      {
        "name": "serverType",
        "type": "string",
        "hasGetter": true,
        "hasSetter": false,
        "isReadonly": true
      }
    ],
    "references": [
      {
        "name": "router",
        "targetType": "HTMLElement"
      }
    ],
    "collections": [],
    "methods": [
      {
        "name": "connectedCallback",
        "parameters": [],
        "returnType": "void",
        "isAsync": false,
        "isAction": false,
        "actionMetadata": null
      },
      {
        "name": "statusFetch",
        "parameters": [],
        "returnType": "void",
        "isAsync": false,
        "isAction": false,
        "actionMetadata": null
      },
      {
        "name": "iorLoadHealth",
        "parameters": [
          {
            "name": "ior",
            "type": "IOR",
            "optional": false,
            "defaultValue": null
          }
        ],
        "returnType": "void",
        "isAsync": false,
        "isAction": false,
        "actionMetadata": null
      },
      {
        "name": "healthDataHandle",
        "parameters": [
          {
            "name": "data",
            "type": "any",
            "optional": false,
            "defaultValue": null
          }
        ],
        "returnType": "void",
        "isAsync": false,
        "isAction": false,
        "actionMetadata": null
      },
      {
        "name": "healthErrorHandle",
        "parameters": [
          {
            "name": "error",
            "type": "Error",
            "optional": false,
            "defaultValue": null
          }
        ],
        "returnType": "void",
        "isAsync": false,
        "isAction": false,
        "actionMetadata": null
      },
      {
        "name": "render",
        "parameters": [],
        "returnType": "TemplateResult",
        "isAsync": false,
        "isAction": false,
        "actionMetadata": null
      }
    ],
    "component": "ONCE",
    "version": "0.3.22.2",
    "createdAt": "2026-01-04T17:09:07.275Z",
    "updatedAt": "2026-01-04T17:09:07.275Z",
    "isInterface": false,
    "isAbstract": false
  }
}