{
  "ior": {
    "uuid": "0028bba9-a856-4cc0-9f86-0834372d2b75",
    "component": "Unit",
    "version": "0.3.22.2"
  },
  "owner": "system",
  "model": {
    "uuid": "0028bba9-a856-4cc0-9f86-0834372d2b75",
    "name": "ManifestRoute.js",
    "typeM3": "CLASS",
    "origin": "ior:git:github.com/Cerulean-Circle-GmbH/UpDown/blob/dev/web4v0100/components/ONCE/0.3.22.2/src/ts/layer2/ManifestRoute.ts",
    "definition": "TypeScript ManifestRoute class/interface",
    "filePath": "dist/ts/layer2/ManifestRoute.js",
    "mimetype": "application/javascript",
    "createdAt": "2026-01-06T11:32:16.535Z",
    "updatedAt": "2026-01-06T11:32:16.535Z",
    "indexPath": "/Users/Shared/Workspaces/2cuGitHub/UpDown/scenarios/index/0/0/2/8/b/0028bba9-a856-4cc0-9f86-0834372d2b75.scenario.json",
    "symlinkPaths": [
      "type/Unit/0.3.22.2"
    ]
  },
  "unit": {
    "indexPath": "0/0/2/8/b/0028bba9-a856-4cc0-9f86-0834372d2b75.scenario.json",
    "symlinkPaths": [
      "type/Unit/0.3.22.2"
    ],
    "references": [],
    "schemaVersion": "1.1.0",
    "createdBy": "Unit/0.3.22.2",
    "createdAt": "2026-01-06T11:32:16.535Z",
    "updatedAt": "2026-01-06T11:32:16.535Z"
  }
}