{
  "ior": {
    "uuid": "8ea18de3-fb72-4153-9379-ee29e4dfd1d2",
    "component": "Unit",
    "version": "0.3.22.2"
  },
  "owner": "system",
  "model": {
    "uuid": "8ea18de3-fb72-4153-9379-ee29e4dfd1d2",
    "name": "TypeDescriptor.js",
    "typeM3": "CLASS",
    "origin": "ior:git:github.com/Cerulean-Circle-GmbH/UpDown/blob/dev/web4v0100/components/ONCE/0.3.22.2/src/ts/layer3/TypeDescriptor.ts",
    "definition": "TypeScript TypeDescriptor class/interface",
    "filePath": "dist/ts/layer3/TypeDescriptor.js",
    "mimetype": "application/javascript",
    "createdAt": "2026-01-09T12:41:20.049Z",
    "updatedAt": "2026-01-09T12:41:20.049Z",
    "indexPath": "/Users/Shared/Workspaces/2cuGitHub/UpDown/scenarios/index/8/e/a/1/8/8ea18de3-fb72-4153-9379-ee29e4dfd1d2.scenario.json",
    "symlinkPaths": [
      "type/Unit/0.3.22.2"
    ]
  },
  "unit": {
    "indexPath": "8/e/a/1/8/8ea18de3-fb72-4153-9379-ee29e4dfd1d2.scenario.json",
    "symlinkPaths": [
      "type/Unit/0.3.22.2"
    ],
    "references": [],
    "schemaVersion": "1.1.0",
    "createdBy": "Unit/0.3.22.2",
    "createdAt": "2026-01-09T12:41:20.049Z",
    "updatedAt": "2026-01-09T12:41:20.049Z"
  }
}