{
  "ior": {
    "uuid": "4b94c69b-4764-41b8-959a-5bc49f6e49d7",
    "component": "Unit",
    "version": "0.3.22.2"
  },
  "owner": "system",
  "model": {
    "uuid": "4b94c69b-4764-41b8-959a-5bc49f6e49d7",
    "name": "ComponentQuery.interface.ts",
    "typeM3": "CLASS",
    "origin": "ior:git:github.com/Cerulean-Circle-GmbH/UpDown/blob/dev/web4v0100/components/ONCE/0.3.22.2/src/ts/layer3/ComponentQuery.interface.ts",
    "definition": "TypeScript ComponentQuery.interface class/interface",
    "filePath": "src/ts/layer3/ComponentQuery.interface.ts",
    "mimetype": "text/typescript",
    "createdAt": "2026-01-06T11:21:39.595Z",
    "updatedAt": "2026-01-06T11:21:39.596Z",
    "indexPath": "/Users/Shared/Workspaces/2cuGitHub/UpDown/scenarios/index/4/b/9/4/c/4b94c69b-4764-41b8-959a-5bc49f6e49d7.scenario.json",
    "symlinkPaths": [
      "type/Unit/0.3.22.2"
    ]
  },
  "unit": {
    "indexPath": "4/b/9/4/c/4b94c69b-4764-41b8-959a-5bc49f6e49d7.scenario.json",
    "symlinkPaths": [
      "type/Unit/0.3.22.2"
    ],
    "references": [],
    "schemaVersion": "1.1.0",
    "createdBy": "Unit/0.3.22.2",
    "createdAt": "2026-01-06T11:21:39.595Z",
    "updatedAt": "2026-01-06T11:21:39.595Z"
  }
}