{
  "ior": {
    "uuid": "77b2b7d7-4dd5-4f4d-acd2-0869c34517c3",
    "component": "Unit",
    "version": "0.3.22.2"
  },
  "owner": "system",
  "model": {
    "uuid": "77b2b7d7-4dd5-4f4d-acd2-0869c34517c3",
    "name": "Loader.interface.js",
    "typeM3": "CLASS",
    "origin": "ior:git:github.com/Cerulean-Circle-GmbH/UpDown/blob/dev/web4v0100/components/ONCE/0.3.22.2/src/ts/layer3/Loader.interface.ts",
    "definition": "TypeScript Loader.interface class/interface",
    "filePath": "dist/ts/layer3/Loader.interface.js",
    "mimetype": "application/javascript",
    "createdAt": "2026-01-08T11:15:24.201Z",
    "updatedAt": "2026-01-08T11:15:24.202Z",
    "indexPath": "/Users/Shared/Workspaces/2cuGitHub/UpDown/scenarios/index/7/7/b/2/b/77b2b7d7-4dd5-4f4d-acd2-0869c34517c3.scenario.json",
    "symlinkPaths": [
      "type/Unit/0.3.22.2"
    ]
  },
  "unit": {
    "indexPath": "7/7/b/2/b/77b2b7d7-4dd5-4f4d-acd2-0869c34517c3.scenario.json",
    "symlinkPaths": [
      "type/Unit/0.3.22.2"
    ],
    "references": [],
    "schemaVersion": "1.1.0",
    "createdBy": "Unit/0.3.22.2",
    "createdAt": "2026-01-08T11:15:24.201Z",
    "updatedAt": "2026-01-08T11:15:24.201Z"
  }
}