{
  "ior": {
    "uuid": "00d206b1-523d-45ef-908a-3f9faa384f42",
    "component": "Unit",
    "version": "0.3.22.2"
  },
  "owner": "system",
  "model": {
    "uuid": "00d206b1-523d-45ef-908a-3f9faa384f42",
    "name": "ServiceWorkerModel.interface.js",
    "typeM3": "CLASS",
    "origin": "ior:git:github.com/Cerulean-Circle-GmbH/UpDown/blob/dev/web4v0100/components/ONCE/0.3.22.2/src/ts/layer3/ServiceWorkerModel.interface.ts",
    "definition": "TypeScript ServiceWorkerModel.interface class/interface",
    "filePath": "dist/ts/layer3/ServiceWorkerModel.interface.js",
    "mimetype": "application/javascript",
    "createdAt": "2026-01-08T11:37:04.936Z",
    "updatedAt": "2026-01-08T11:37:04.936Z",
    "indexPath": "/Users/Shared/Workspaces/2cuGitHub/UpDown/scenarios/index/0/0/d/2/0/00d206b1-523d-45ef-908a-3f9faa384f42.scenario.json",
    "symlinkPaths": [
      "type/Unit/0.3.22.2"
    ]
  },
  "unit": {
    "indexPath": "0/0/d/2/0/00d206b1-523d-45ef-908a-3f9faa384f42.scenario.json",
    "symlinkPaths": [
      "type/Unit/0.3.22.2"
    ],
    "references": [],
    "schemaVersion": "1.1.0",
    "createdBy": "Unit/0.3.22.2",
    "createdAt": "2026-01-08T11:37:04.936Z",
    "updatedAt": "2026-01-08T11:37:04.936Z"
  }
}