{"ior":{"uuid":"ef879ee3-a321-451d-9812-873cb475c4f3","component":"Unit","version":"0.3.22.1"},"owner":"system","model":{"uuid":"ef879ee3-a321-451d-9812-873cb475c4f3","name":"FileLoader.js","typeM3":"CLASS","origin":"ior:git:github.com/Cerulean-Circle-GmbH/UpDown/blob/dev/web4v0100/components/ONCE/0.3.22.1/src/ts/layer4/FileLoader.ts","definition":"TypeScript FileLoader class/interface","filePath":"dist/ts/layer4/FileLoader.js","mimetype":"application/javascript","createdAt":"2026-01-01T19:02:21.191Z","updatedAt":"2026-01-01T19:02:21.191Z","indexPath":"/Users/Shared/Workspaces/2cuGitHub/UpDown/scenarios/index/e/f/8/7/9/ef879ee3-a321-451d-9812-873cb475c4f3.scenario.json","symlinkPaths":["type/Unit/0.3.22.1"]},"unit":{"indexPath":"e/f/8/7/9/ef879ee3-a321-451d-9812-873cb475c4f3.scenario.json","symlinkPaths":["type/Unit/0.3.22.1"],"references":[],"schemaVersion":"1.1.0","createdBy":"Unit/0.3.22.1","createdAt":"2026-01-01T19:02:21.191Z","updatedAt":"2026-01-01T19:02:21.191Z"}}