{
  "ior": {
    "uuid": "4a393539-d912-435d-a059-3788490853a5",
    "component": "Unit",
    "version": "0.3.22.2"
  },
  "owner": "system",
  "model": {
    "uuid": "4a393539-d912-435d-a059-3788490853a5",
    "name": "UserModel.interface.js",
    "typeM3": "CLASS",
    "origin": "ior:git:github.com/Cerulean-Circle-GmbH/UpDown/blob/dev/web4v0100/components/ONCE/0.3.22.2/src/ts/layer3/UserModel.interface.ts",
    "definition": "TypeScript UserModel.interface class/interface",
    "filePath": "dist/ts/layer3/UserModel.interface.js",
    "mimetype": "application/javascript",
    "createdAt": "2026-01-08T11:37:04.967Z",
    "updatedAt": "2026-01-08T11:37:04.967Z",
    "indexPath": "/Users/Shared/Workspaces/2cuGitHub/UpDown/scenarios/index/4/a/3/9/3/4a393539-d912-435d-a059-3788490853a5.scenario.json",
    "symlinkPaths": [
      "type/Unit/0.3.22.2"
    ]
  },
  "unit": {
    "indexPath": "4/a/3/9/3/4a393539-d912-435d-a059-3788490853a5.scenario.json",
    "symlinkPaths": [
      "type/Unit/0.3.22.2"
    ],
    "references": [],
    "schemaVersion": "1.1.0",
    "createdBy": "Unit/0.3.22.2",
    "createdAt": "2026-01-08T11:37:04.967Z",
    "updatedAt": "2026-01-08T11:37:04.967Z"
  }
}