{
  "ior": {
    "uuid": "b5445856-742e-4e60-a88c-8e6fb41c0ec9",
    "component": "Unit",
    "version": "0.3.22.2"
  },
  "owner": "system",
  "model": {
    "uuid": "b5445856-742e-4e60-a88c-8e6fb41c0ec9",
    "name": "LoaderModel.interface.js",
    "typeM3": "CLASS",
    "origin": "ior:git:github.com/Cerulean-Circle-GmbH/UpDown/blob/dev/web4v0100/components/ONCE/0.3.22.2/src/ts/layer3/LoaderModel.interface.ts",
    "definition": "TypeScript LoaderModel.interface class/interface",
    "filePath": "dist/ts/layer3/LoaderModel.interface.js",
    "mimetype": "application/javascript",
    "createdAt": "2026-01-08T11:27:22.661Z",
    "updatedAt": "2026-01-08T11:27:22.661Z",
    "indexPath": "/Users/Shared/Workspaces/2cuGitHub/UpDown/scenarios/index/b/5/4/4/5/b5445856-742e-4e60-a88c-8e6fb41c0ec9.scenario.json",
    "symlinkPaths": [
      "type/Unit/0.3.22.2"
    ]
  },
  "unit": {
    "indexPath": "b/5/4/4/5/b5445856-742e-4e60-a88c-8e6fb41c0ec9.scenario.json",
    "symlinkPaths": [
      "type/Unit/0.3.22.2"
    ],
    "references": [],
    "schemaVersion": "1.1.0",
    "createdBy": "Unit/0.3.22.2",
    "createdAt": "2026-01-08T11:27:22.661Z",
    "updatedAt": "2026-01-08T11:27:22.661Z"
  }
}