{
  "ior": {
    "uuid": "d7840656-f814-4b92-b0e7-35b044c6d051",
    "component": "Unit",
    "version": "0.0.0.0"
  },
  "owner": "system",
  "model": {
    "uuid": "d7840656-f814-4b92-b0e7-35b044c6d051",
    "name": "UnitCacheManagerModel.interface.ts",
    "typeM3": "CLASS",
    "origin": "ior:git:github.com/Cerulean-Circle-GmbH/UpDown/blob/dev/web4v0100/components/ONCE/0.0.0.0/src/ts/layer3/UnitCacheManagerModel.interface.ts",
    "definition": "TypeScript UnitCacheManagerModel.interface class/interface",
    "filePath": "src/ts/layer3/UnitCacheManagerModel.interface.ts",
    "mimetype": "text/typescript",
    "createdAt": "2026-01-06T15:10:49.458Z",
    "updatedAt": "2026-01-06T15:10:49.458Z",
    "indexPath": "/Users/Shared/Workspaces/2cuGitHub/UpDown/scenarios/index/d/7/8/4/0/d7840656-f814-4b92-b0e7-35b044c6d051.scenario.json",
    "symlinkPaths": [
      "type/Unit/0.0.0.0"
    ]
  },
  "unit": {
    "indexPath": "d/7/8/4/0/d7840656-f814-4b92-b0e7-35b044c6d051.scenario.json",
    "symlinkPaths": [
      "type/Unit/0.0.0.0"
    ],
    "references": [],
    "schemaVersion": "1.1.0",
    "createdBy": "Unit/0.0.0.0",
    "createdAt": "2026-01-06T15:10:49.458Z",
    "updatedAt": "2026-01-06T15:10:49.458Z"
  }
}