{
  "ior": {
    "uuid": "e030a961-6357-4416-a31d-d3b73295ed9e",
    "component": "Unit",
    "version": "0.3.22.2"
  },
  "owner": "system",
  "model": {
    "uuid": "e030a961-6357-4416-a31d-d3b73295ed9e",
    "name": "WebSocketLoader.ts",
    "typeM3": "CLASS",
    "origin": "ior:git:github.com/Cerulean-Circle-GmbH/UpDown/blob/dev/web4v0100/components/ONCE/0.3.22.2/src/ts/layer4/WebSocketLoader.ts",
    "definition": "TypeScript WebSocketLoader class/interface",
    "filePath": "src/ts/layer4/WebSocketLoader.ts",
    "mimetype": "text/typescript",
    "createdAt": "2026-01-08T11:37:04.508Z",
    "updatedAt": "2026-01-08T11:37:04.508Z",
    "indexPath": "/Users/Shared/Workspaces/2cuGitHub/UpDown/scenarios/index/e/0/3/0/a/e030a961-6357-4416-a31d-d3b73295ed9e.scenario.json",
    "symlinkPaths": [
      "type/Unit/0.3.22.2"
    ]
  },
  "unit": {
    "indexPath": "e/0/3/0/a/e030a961-6357-4416-a31d-d3b73295ed9e.scenario.json",
    "symlinkPaths": [
      "type/Unit/0.3.22.2"
    ],
    "references": [],
    "schemaVersion": "1.1.0",
    "createdBy": "Unit/0.3.22.2",
    "createdAt": "2026-01-08T11:37:04.508Z",
    "updatedAt": "2026-01-08T11:37:04.508Z"
  }
}