{
  "ior": {
    "uuid": "f1e1d88d-ba4f-4da6-a57f-9fa8ec0fbc43",
    "component": "Unit",
    "version": "0.3.22.2"
  },
  "owner": "system",
  "model": {
    "uuid": "f1e1d88d-ba4f-4da6-a57f-9fa8ec0fbc43",
    "name": "Component.interface.ts",
    "typeM3": "CLASS",
    "origin": "ior:git:github.com/Cerulean-Circle-GmbH/UpDown/blob/dev/web4v0100/components/ONCE/0.3.22.2/src/ts/layer3/Component.interface.ts",
    "definition": "TypeScript Component.interface class/interface",
    "filePath": "src/ts/layer3/Component.interface.ts",
    "mimetype": "text/typescript",
    "createdAt": "2026-01-06T11:32:15.304Z",
    "updatedAt": "2026-01-06T11:32:15.304Z",
    "indexPath": "/Users/Shared/Workspaces/2cuGitHub/UpDown/scenarios/index/f/1/e/1/d/f1e1d88d-ba4f-4da6-a57f-9fa8ec0fbc43.scenario.json",
    "symlinkPaths": [
      "type/Unit/0.3.22.2"
    ]
  },
  "unit": {
    "indexPath": "f/1/e/1/d/f1e1d88d-ba4f-4da6-a57f-9fa8ec0fbc43.scenario.json",
    "symlinkPaths": [
      "type/Unit/0.3.22.2"
    ],
    "references": [],
    "schemaVersion": "1.1.0",
    "createdBy": "Unit/0.3.22.2",
    "createdAt": "2026-01-06T11:32:15.304Z",
    "updatedAt": "2026-01-06T11:32:15.304Z"
  }
}