{
  "ior": {
    "uuid": "0d92c132-cf24-42e7-b5ae-ef4d49e891b7",
    "component": "ONCE",
    "version": "0.3.22.2"
  },
  "owner": "TsAstExtractor",
  "model": {
    "uuid": "0d92c132-cf24-42e7-b5ae-ef4d49e891b7",
    "name": "DomainCertificateStoreModel",
    "extends": null,
    "implements": [],
    "sourcePath": "src/ts/layer3/DomainCertificateStoreModel.interface.ts",
    "indexPath": "scenarios/index/0d92c132-cf24-42e7-b5ae-ef4d49e891b7.type.scenario.json",
    "symlinkPaths": [
      "scenarios/type/DomainCertificateStoreModel.type.scenario.json"
    ],
    "attributes": [
      {
        "name": "uuid",
        "type": "string",
        "optional": false,
        "defaultValue": null
      },
      {
        "name": "name",
        "type": "string",
        "optional": false,
        "defaultValue": null
      },
      {
        "name": "iorComponent",
        "type": "string",
        "optional": true,
        "defaultValue": null
      },
      {
        "name": "iorVersion",
        "type": "string",
        "optional": true,
        "defaultValue": null
      },
      {
        "name": "scenariosRootPath",
        "type": "string",
        "optional": false,
        "defaultValue": null
      },
      {
        "name": "providerName",
        "type": "string",
        "optional": false,
        "defaultValue": null
      },
      {
        "name": "providerVersion",
        "type": "string",
        "optional": false,
        "defaultValue": null
      },
      {
        "name": "statistics",
        "type": "StatisticsModel",
        "optional": false,
        "defaultValue": null
      }
    ],
    "properties": [],
    "references": [],
    "collections": [],
    "methods": [],
    "component": "ONCE",
    "version": "0.3.22.2",
    "createdAt": "2026-01-08T12:12:21.067Z",
    "updatedAt": "2026-01-08T12:12:21.067Z",
    "isInterface": true,
    "isAbstract": false
  }
}