{
  "ior": {
    "uuid": "31c6750f-c82e-4195-a084-34a181f6f307",
    "component": "ONCE",
    "version": "0.3.22.2"
  },
  "owner": "TsAstExtractor",
  "model": {
    "uuid": "31c6750f-c82e-4195-a084-34a181f6f307",
    "name": "AbstractDefaultView",
    "extends": "ior:esm:/ONCE/0.3.22.2/AbstractView",
    "implements": [],
    "sourcePath": "src/ts/layer3/AbstractDefaultView.ts",
    "indexPath": "scenarios/index/31c6750f-c82e-4195-a084-34a181f6f307.type.scenario.json",
    "symlinkPaths": [
      "scenarios/type/AbstractDefaultView.type.scenario.json"
    ],
    "attributes": [],
    "properties": [
      {
        "name": "title",
        "type": "string",
        "hasGetter": true,
        "hasSetter": false,
        "isReadonly": true
      },
      {
        "name": "subtitle",
        "type": "string",
        "hasGetter": true,
        "hasSetter": false,
        "isReadonly": true
      },
      {
        "name": "actions",
        "type": "string[]",
        "hasGetter": true,
        "hasSetter": false,
        "isReadonly": true
      }
    ],
    "references": [],
    "collections": [],
    "methods": [],
    "component": "ONCE",
    "version": "0.3.22.2",
    "createdAt": "2026-01-08T12:12:21.023Z",
    "updatedAt": "2026-01-08T12:12:21.023Z",
    "isInterface": false,
    "isAbstract": true
  }
}