{
  "ior": {
    "uuid": "394c9580-17d7-424f-a1f4-231d4b61924a",
    "component": "Unit",
    "version": "0.3.22.2"
  },
  "owner": "system",
  "model": {
    "uuid": "394c9580-17d7-424f-a1f4-231d4b61924a",
    "name": "ImageModel.interface.js",
    "typeM3": "CLASS",
    "origin": "ior:git:github.com/Cerulean-Circle-GmbH/UpDown/blob/dev/web4v0100/components/ONCE/0.3.22.2/src/ts/layer3/ImageModel.interface.ts",
    "definition": "TypeScript ImageModel.interface class/interface",
    "filePath": "dist/ts/layer3/ImageModel.interface.js",
    "mimetype": "application/javascript",
    "createdAt": "2026-01-08T11:15:24.175Z",
    "updatedAt": "2026-01-08T11:15:24.175Z",
    "indexPath": "/Users/Shared/Workspaces/2cuGitHub/UpDown/scenarios/index/3/9/4/c/9/394c9580-17d7-424f-a1f4-231d4b61924a.scenario.json",
    "symlinkPaths": [
      "type/Unit/0.3.22.2"
    ]
  },
  "unit": {
    "indexPath": "3/9/4/c/9/394c9580-17d7-424f-a1f4-231d4b61924a.scenario.json",
    "symlinkPaths": [
      "type/Unit/0.3.22.2"
    ],
    "references": [],
    "schemaVersion": "1.1.0",
    "createdBy": "Unit/0.3.22.2",
    "createdAt": "2026-01-08T11:15:24.175Z",
    "updatedAt": "2026-01-08T11:15:24.175Z"
  }
}