{"ior":{"uuid":"c7f25e0a-ac88-442b-b317-5311df010a9c","component":"Unit","version":"0.3.22.1"},"owner":"system","model":{"uuid":"c7f25e0a-ac88-442b-b317-5311df010a9c","name":"Container.interface.ts","typeM3":"CLASS","origin":"ior:git:github.com/Cerulean-Circle-GmbH/UpDown/blob/dev/web4v0100/components/ONCE/0.3.22.1/src/ts/layer3/Container.interface.ts","definition":"TypeScript Container.interface class/interface","filePath":"src/ts/layer3/Container.interface.ts","mimetype":"text/typescript","createdAt":"2026-01-01T18:33:57.372Z","updatedAt":"2026-01-01T18:33:57.373Z","indexPath":"/Users/Shared/Workspaces/2cuGitHub/UpDown/scenarios/index/c/7/f/2/5/c7f25e0a-ac88-442b-b317-5311df010a9c.scenario.json","symlinkPaths":["type/Unit/0.3.22.1"]},"unit":{"indexPath":"c/7/f/2/5/c7f25e0a-ac88-442b-b317-5311df010a9c.scenario.json","symlinkPaths":["type/Unit/0.3.22.1"],"references":[],"schemaVersion":"1.1.0","createdBy":"Unit/0.3.22.1","createdAt":"2026-01-01T18:33:57.372Z","updatedAt":"2026-01-01T18:33:57.372Z"}}