{"ior":{"uuid":"e03cb129-71df-47a4-a29a-c41700aac123","component":"Unit","version":"0.3.22.1"},"owner":"system","model":{"uuid":"e03cb129-71df-47a4-a29a-c41700aac123","name":"ScenarioManager.ts","typeM3":"CLASS","origin":"ior:git:github.com/Cerulean-Circle-GmbH/UpDown/blob/dev/web4v0100/components/ONCE/0.3.22.1/src/ts/layer2/ScenarioManager.ts","definition":"TypeScript ScenarioManager class/interface","filePath":"src/ts/layer2/ScenarioManager.ts","mimetype":"text/typescript","createdAt":"2026-01-01T19:38:19.320Z","updatedAt":"2026-01-01T19:38:19.321Z","indexPath":"/Users/Shared/Workspaces/2cuGitHub/UpDown/scenarios/index/e/0/3/c/b/e03cb129-71df-47a4-a29a-c41700aac123.scenario.json","symlinkPaths":["type/Unit/0.3.22.1"]},"unit":{"indexPath":"e/0/3/c/b/e03cb129-71df-47a4-a29a-c41700aac123.scenario.json","symlinkPaths":["type/Unit/0.3.22.1"],"references":[],"schemaVersion":"1.1.0","createdBy":"Unit/0.3.22.1","createdAt":"2026-01-01T19:38:19.320Z","updatedAt":"2026-01-01T19:38:19.320Z"}}