{
  "ior": {
    "uuid": "988586bc-e688-43fc-aafc-eb472e059890",
    "component": "Unit",
    "version": "0.3.22.1"
  },
  "owner": "system",
  "model": {
    "uuid": "988586bc-e688-43fc-aafc-eb472e059890",
    "name": "CollectionDescriptor.interface.js",
    "typeM3": "CLASS",
    "origin": "ior:git:github.com/Cerulean-Circle-GmbH/UpDown/blob/dev/web4v0100/components/ONCE/0.3.22.1/src/ts/layer3/CollectionDescriptor.interface.ts",
    "definition": "TypeScript CollectionDescriptor.interface class/interface",
    "filePath": "dist/ts/layer3/CollectionDescriptor.interface.js",
    "mimetype": "application/javascript",
    "createdAt": "2026-01-02T11:56:30.636Z",
    "updatedAt": "2026-01-02T11:56:30.636Z",
    "indexPath": "/Users/Shared/Workspaces/2cuGitHub/UpDown/scenarios/index/9/8/8/5/8/988586bc-e688-43fc-aafc-eb472e059890.scenario.json",
    "symlinkPaths": [
      "type/Unit/0.3.22.1"
    ]
  },
  "unit": {
    "indexPath": "9/8/8/5/8/988586bc-e688-43fc-aafc-eb472e059890.scenario.json",
    "symlinkPaths": [
      "type/Unit/0.3.22.1"
    ],
    "references": [],
    "schemaVersion": "1.1.0",
    "createdBy": "Unit/0.3.22.1",
    "createdAt": "2026-01-02T11:56:30.636Z",
    "updatedAt": "2026-01-02T11:56:30.636Z"
  }
}