{
  "ior": {
    "uuid": "8ffb5444-2776-48d8-b43b-0abf786f5d22",
    "component": "Unit",
    "version": "0.3.22.2"
  },
  "owner": "system",
  "model": {
    "uuid": "8ffb5444-2776-48d8-b43b-0abf786f5d22",
    "name": "CSSLoader.js",
    "typeM3": "CLASS",
    "origin": "ior:git:github.com/Cerulean-Circle-GmbH/UpDown/blob/dev/web4v0100/components/ONCE/0.3.22.2/src/ts/layer2/CSSLoader.ts",
    "definition": "TypeScript CSSLoader class/interface",
    "filePath": "dist/ts/layer2/CSSLoader.js",
    "mimetype": "application/javascript",
    "createdAt": "2026-01-08T11:44:31.440Z",
    "updatedAt": "2026-01-08T11:44:31.440Z",
    "indexPath": "/Users/Shared/Workspaces/2cuGitHub/UpDown/scenarios/index/8/f/f/b/5/8ffb5444-2776-48d8-b43b-0abf786f5d22.scenario.json",
    "symlinkPaths": [
      "type/Unit/0.3.22.2"
    ]
  },
  "unit": {
    "indexPath": "8/f/f/b/5/8ffb5444-2776-48d8-b43b-0abf786f5d22.scenario.json",
    "symlinkPaths": [
      "type/Unit/0.3.22.2"
    ],
    "references": [],
    "schemaVersion": "1.1.0",
    "createdBy": "Unit/0.3.22.2",
    "createdAt": "2026-01-08T11:44:31.440Z",
    "updatedAt": "2026-01-08T11:44:31.440Z"
  }
}