{
  "ior": {
    "uuid": "b26d9961-9656-4f3f-b22c-b5a9d80afb53",
    "component": "Unit",
    "version": "0.3.22.2"
  },
  "owner": "system",
  "model": {
    "uuid": "b26d9961-9656-4f3f-b22c-b5a9d80afb53",
    "name": "ErrorRoute.ts",
    "typeM3": "CLASS",
    "origin": "ior:git:github.com/Cerulean-Circle-GmbH/UpDown/blob/dev/web4v0100/components/ONCE/0.3.22.2/src/ts/layer2/ErrorRoute.ts",
    "definition": "TypeScript ErrorRoute class/interface",
    "filePath": "src/ts/layer2/ErrorRoute.ts",
    "mimetype": "text/typescript",
    "createdAt": "2026-01-08T12:14:22.428Z",
    "updatedAt": "2026-01-08T12:14:22.428Z",
    "indexPath": "/Users/Shared/Workspaces/2cuGitHub/UpDown/scenarios/index/b/2/6/d/9/b26d9961-9656-4f3f-b22c-b5a9d80afb53.scenario.json",
    "symlinkPaths": [
      "type/Unit/0.3.22.2"
    ]
  },
  "unit": {
    "indexPath": "b/2/6/d/9/b26d9961-9656-4f3f-b22c-b5a9d80afb53.scenario.json",
    "symlinkPaths": [
      "type/Unit/0.3.22.2"
    ],
    "references": [],
    "schemaVersion": "1.1.0",
    "createdBy": "Unit/0.3.22.2",
    "createdAt": "2026-01-08T12:14:22.428Z",
    "updatedAt": "2026-01-08T12:14:22.428Z"
  }
}