{
  "ior": {
    "uuid": "af9b2b7f-5c3f-42ae-890f-50c14654f0ab",
    "component": "Unit",
    "version": "0.3.22.2"
  },
  "owner": "system",
  "model": {
    "uuid": "af9b2b7f-5c3f-42ae-890f-50c14654f0ab",
    "name": "LifecycleSubject.interface.js",
    "typeM3": "CLASS",
    "origin": "ior:git:github.com/Cerulean-Circle-GmbH/UpDown/blob/dev/web4v0100/components/ONCE/0.3.22.2/src/ts/layer3/LifecycleSubject.interface.ts",
    "definition": "TypeScript LifecycleSubject.interface class/interface",
    "filePath": "dist/ts/layer3/LifecycleSubject.interface.js",
    "mimetype": "application/javascript",
    "createdAt": "2026-01-08T12:17:32.632Z",
    "updatedAt": "2026-01-08T12:17:32.633Z",
    "indexPath": "/Users/Shared/Workspaces/2cuGitHub/UpDown/scenarios/index/a/f/9/b/2/af9b2b7f-5c3f-42ae-890f-50c14654f0ab.scenario.json",
    "symlinkPaths": [
      "type/Unit/0.3.22.2"
    ]
  },
  "unit": {
    "indexPath": "a/f/9/b/2/af9b2b7f-5c3f-42ae-890f-50c14654f0ab.scenario.json",
    "symlinkPaths": [
      "type/Unit/0.3.22.2"
    ],
    "references": [],
    "schemaVersion": "1.1.0",
    "createdBy": "Unit/0.3.22.2",
    "createdAt": "2026-01-08T12:17:32.632Z",
    "updatedAt": "2026-01-08T12:17:32.632Z"
  }
}