{"ior":{"uuid":"8c357a41-3bb3-4c24-a80d-c33ce74af6d8","component":"Unit","version":"0.3.22.1"},"owner":"system","model":{"uuid":"8c357a41-3bb3-4c24-a80d-c33ce74af6d8","name":"Storage.interface.ts","typeM3":"CLASS","origin":"ior:git:github.com/Cerulean-Circle-GmbH/UpDown/blob/dev/web4v0100/components/ONCE/0.3.22.1/src/ts/layer3/Storage.interface.ts","definition":"TypeScript Storage.interface class/interface","filePath":"src/ts/layer3/Storage.interface.ts","mimetype":"text/typescript","createdAt":"2026-01-01T18:33:57.587Z","updatedAt":"2026-01-01T18:33:57.587Z","indexPath":"/Users/Shared/Workspaces/2cuGitHub/UpDown/scenarios/index/8/c/3/5/7/8c357a41-3bb3-4c24-a80d-c33ce74af6d8.scenario.json","symlinkPaths":["type/Unit/0.3.22.1"]},"unit":{"indexPath":"8/c/3/5/7/8c357a41-3bb3-4c24-a80d-c33ce74af6d8.scenario.json","symlinkPaths":["type/Unit/0.3.22.1"],"references":[],"schemaVersion":"1.1.0","createdBy":"Unit/0.3.22.1","createdAt":"2026-01-01T18:33:57.587Z","updatedAt":"2026-01-01T18:33:57.587Z"}}