{"ior":{"uuid":"ff0e3a2e-27a9-43b4-a13e-c81cda01a41d","component":"Unit","version":"0.3.22.1"},"owner":"system","model":{"uuid":"ff0e3a2e-27a9-43b4-a13e-c81cda01a41d","name":"NodeJsOnce.js","typeM3":"CLASS","origin":"ior:git:github.com/Cerulean-Circle-GmbH/UpDown/blob/dev/web4v0100/components/ONCE/0.3.22.1/src/ts/layer2/NodeJsOnce.ts","definition":"TypeScript NodeJsOnce class/interface","filePath":"dist/ts/layer2/NodeJsOnce.js","mimetype":"application/javascript","createdAt":"2026-01-01T19:01:07.137Z","updatedAt":"2026-01-01T19:01:07.138Z","indexPath":"/Users/Shared/Workspaces/2cuGitHub/UpDown/scenarios/index/f/f/0/e/3/ff0e3a2e-27a9-43b4-a13e-c81cda01a41d.scenario.json","symlinkPaths":["type/Unit/0.3.22.1"]},"unit":{"indexPath":"f/f/0/e/3/ff0e3a2e-27a9-43b4-a13e-c81cda01a41d.scenario.json","symlinkPaths":["type/Unit/0.3.22.1"],"references":[],"schemaVersion":"1.1.0","createdBy":"Unit/0.3.22.1","createdAt":"2026-01-01T19:01:07.137Z","updatedAt":"2026-01-01T19:01:07.137Z"}}